peakfit/__init__.py
peakfit/__main__.py
peakfit/cli.py
peakfit/clustering.py
peakfit/computing.py
peakfit/messages.py
peakfit/nmrpipe.py
peakfit/noise.py
peakfit/peak.py
peakfit/peakfit.py
peakfit/peaklist.py
peakfit/shapes.py
peakfit/spectra.py
peakfit/typing.py
peakfit/writing.py
peakfit/plotting/__init__.py
peakfit/plotting/common.py
peakfit/plotting/main.py
peakfit/plotting/plots/__init__.py
peakfit/plotting/plots/cest.py
peakfit/plotting/plots/cpmg.py
peakfit/plotting/plots/intensity.py
peakfit/plotting/plots/spectra.py
peakfit-0.10.5.dist-info/METADATA
peakfit-0.10.5.dist-info/WHEEL
peakfit-0.10.5.dist-info/entry_points.txt
peakfit-0.10.5.dist-info/licenses/LICENSE
peakfit-0.10.5.dist-info/RECORD
