Metadata-Version: 2.4
Name: PeakFit
Version: 0.10.5
Summary: PeakFit allow for lineshape fitting in pseudo-3D NMR spectra.
Author-email: Guillaume Bouvignies <guillaume.bouvignies@ens.psl.eu>
License: GPL-3.0-or-later
License-File: LICENSE
Requires-Python: >=3.12
Requires-Dist: emcee>=3.1.6
Requires-Dist: lmfit>=1.3.1
Requires-Dist: matplotlib>=3.9.0
Requires-Dist: networkx>=3.3
Requires-Dist: nmrglue>=0.10
Requires-Dist: numdifftools>=0.9.41
Requires-Dist: numpy>=2.0.0
Requires-Dist: pandas[excel]>=2.2.2
Requires-Dist: pyqt5>=5.15.11
Requires-Dist: rich>=13.7.1
Requires-Dist: scipy>=1.13.1
